hahomematic/__init__.py
hahomematic/async_support.py
hahomematic/const.py
hahomematic/context.py
hahomematic/converter.py
hahomematic/decorators.py
hahomematic/exceptions.py
hahomematic/hmcli.py
hahomematic/py.typed
hahomematic/support.py
hahomematic/validator.py
hahomematic/caches/__init__.py
hahomematic/caches/dynamic.py
hahomematic/caches/persistent.py
hahomematic/caches/visibility.py
hahomematic/central/__init__.py
hahomematic/central/decorators.py
hahomematic/central/xml_rpc_server.py
hahomematic/client/__init__.py
hahomematic/client/json_rpc.py
hahomematic/client/xml_rpc.py
hahomematic/model/__init__.py
hahomematic/model/data_point.py
hahomematic/model/decorators.py
hahomematic/model/device.py
hahomematic/model/event.py
hahomematic/model/support.py
hahomematic/model/update.py
hahomematic/model/calculated/__init__.py
hahomematic/model/calculated/climate.py
hahomematic/model/calculated/data_point.py
hahomematic/model/calculated/operating_voltage_level.py
hahomematic/model/calculated/support.py
hahomematic/model/custom/__init__.py
hahomematic/model/custom/climate.py
hahomematic/model/custom/const.py
hahomematic/model/custom/cover.py
hahomematic/model/custom/data_point.py
hahomematic/model/custom/definition.py
hahomematic/model/custom/light.py
hahomematic/model/custom/lock.py
hahomematic/model/custom/siren.py
hahomematic/model/custom/support.py
hahomematic/model/custom/switch.py
hahomematic/model/custom/valve.py
hahomematic/model/generic/__init__.py
hahomematic/model/generic/action.py
hahomematic/model/generic/binary_sensor.py
hahomematic/model/generic/button.py
hahomematic/model/generic/data_point.py
hahomematic/model/generic/number.py
hahomematic/model/generic/select.py
hahomematic/model/generic/sensor.py
hahomematic/model/generic/switch.py
hahomematic/model/generic/text.py
hahomematic/model/hub/__init__.py
hahomematic/model/hub/binary_sensor.py
hahomematic/model/hub/button.py
hahomematic/model/hub/data_point.py
hahomematic/model/hub/number.py
hahomematic-2025.8.5.dist-info/licenses/LICENSE
hahomematic-2025.8.5.dist-info/METADATA
hahomematic-2025.8.5.dist-info/WHEEL
hahomematic-2025.8.5.dist-info/top_level.txt
hahomematic-2025.8.5.dist-info/RECORD
