Metadata-Version: 2.4
Name: hahomematic
Version: 2025.8.5
Summary: Homematic interface for Home Assistant running on Python 3.
Home-page: https://github.com/sukramj/hahomematic
Author-email: SukramJ <sukramj@icloud.com>, Daniel Perna <danielperna84@gmail.com>
License: MIT License
Project-URL: Source Code, https://github.com/sukramj/hahomematic
Project-URL: Bug Reports, https://github.com/sukramj/hahomematic/issues
Project-URL: Docs: Dev, https://github.com/sukramj/hahomematic
Project-URL: Forum, https://github.com/sukramj/hahomematic/discussions
Keywords: home,automation,homematic
Classifier: Development Status :: 5 - Production/Stable
Classifier: Intended Audience :: End Users/Desktop
Classifier: Intended Audience :: Developers
Classifier: License :: OSI Approved :: MIT License
Classifier: Operating System :: OS Independent
Classifier: Programming Language :: Python :: 3.13
Classifier: Topic :: Home Automation
Requires-Python: >=3.13.0
License-File: LICENSE
Requires-Dist: aiohttp>=3.10.0
Requires-Dist: orjson>=3.10.0
Requires-Dist: python-slugify>=8.0.0
Requires-Dist: voluptuous>=0.14.0
Dynamic: license-file
